[
  {
    "id": "pricing-cards",
    "name": "default",
    "docURL": "...",
    "version": "sktwi1xtmkfgx8626",
    "description": "PricingCards",
    "primary": {
      "text": [
        {
          "type": "heading2",
          "text": "Check out our most popular packages",
          "spans": []
        }
      ],
      "buttonLink": {
        "link_type": "Web",
        "url": "https://slicemachine.dev"
      },
      "buttonText": "View all packages"
    },
    "items": [
      {
        "name": "Backer",
        "description": [
          {
            "type": "paragraph",
            "text": "Get your name included in the credits.",
            "spans": []
          }
        ],
        "caption": "",
        "price": 150,
        "buttonLink": {
          "link_type": "Web",
          "url": "https://slicemachine.dev"
        },
        "buttonText": "Purchase"
      },
      {
        "name": "Basic",
        "description": [
          {
            "type": "paragraph",
            "text": "Get your name included in the credits.",
            "spans": []
          },
          {
            "type": "paragraph",
            "text": "Get entry to the beta and a single licence of the final release.",
            "spans": []
          }
        ],
        "caption": "",
        "price": 750,
        "buttonLink": {
          "link_type": "Web",
          "url": "https://slicemachine.dev"
        },
        "buttonText": "Purchase"
      },
      {
        "name": "Ultimate",
        "description": [
          {
            "type": "paragraph",
            "text": "Get your name included in the credits.",
            "spans": []
          },
          {
            "type": "paragraph",
            "text": "Get entry to the beta and a family licence of the final release.",
            "spans": []
          }
        ],
        "caption": "Best Value",
        "price": 1500,
        "buttonLink": {
          "link_type": "Web",
          "url": "https://slicemachine.dev"
        },
        "buttonText": "Purchase"
      }
    ],
    "slice_type": "pricing_cards"
  }
]
