[
  {
    "id": "default-slice",
    "name": "Default slice",
    "docURL": "...",
    "version": "sktwi1xtmkfgx8626",
    "description": "FormContact",
    "primary": {
      "text": [
        {
          "type": "heading1",
          "text": "Drop us a message",
          "spans": []
        },
        {
          "type": "paragraph",
          "text": "Ad cupidatat dolore fugiat dolore irure ullamco. Consectetur voluptate esse do nulla ad id aliquip qui irure elit aliqua qui.",
          "spans": []
        }
      ],
      "apiRoute": "utilize interactive channels"
    },
    "items": [],
    "slice_type": "form_contact"
  }
]
